a5py/__init__.py
a5py/a5_connection.py
a5py/a5py_cli.py
a5py/config.py
a5py/a5_tables/__init__.py
a5py/a5_tables/a5_base.py
a5py/a5_tables/areas.py
a5py/a5_tables/base.py
a5py/a5_tables/observaciones_abstract.py
a5py/a5_tables/observaciones_areal.py
a5py/a5_tables/observaciones_rast.py
a5py/a5_tables/series_abstract.py
a5py/a5_tables/series_areal.py
a5py/a5_tables/series_rast.py
a5py/a5_tables/a5_types/__init__.py
a5py/a5_tables/a5_types/raster.py
a5py/util/__init__.py
a5py/util/util.py
a5py-0.1.4.dist-info/LICENSE
a5py-0.1.4.dist-info/METADATA
a5py-0.1.4.dist-info/WHEEL
a5py-0.1.4.dist-info/entry_points.txt
a5py-0.1.4.dist-info/top_level.txt
a5py-0.1.4.dist-info/RECORD
