Metadata-Version: 2.2
Name: a5py
Version: 0.1.4
Summary: a5 hydrometeorologic database management system
Author-email: "Juan F. Bianchi" <jbianchi@ina.gob.ar>
License: MIT
Project-URL: Homepage, https://github.com/jbianchi81/a5_client
Requires-Python: >=3.10
License-File: LICENSE
Requires-Dist: requests
Requires-Dist: numpy
Requires-Dist: psycopg2
Requires-Dist: sqlalchemy
Requires-Dist: geoalchemy2
Requires-Dist: rasterio
Requires-Dist: shapely
